Metadata-Version: 2.1
Name: vtfcal
Version: 0.3.5
Summary: Calibration pipeline for the DKIST/VTF
Home-page: http://dkist.nso.edu/inst/VTF
Author: Aperio Software Ltd.
Author-email: andrew.leonard@aperiosoftware.com
License: BSD 3-Clause
Platform: UNKNOWN
